{
    "parameters": {
        "p_bias": 0.05,
        "max_step_size": 0.2,
        "runs": 20
    },
    "stats": {
        "intervals": [
            400,
            800,
            1200,
            1600,
            2000
        ],
        "success_rate_percent": [
            35.0,
            40.0,
            40.0,
            50.0,
            55.00000000000001
        ],
        "average_cost": [
            1.264495782687972,
            1.2595561151063275,
            1.2595561151063275,
            1.2535053095447248,
            1.28464546467324
        ]
    },
    "raw_data": [
        {
            "run_id": 0,
            "success": [
                1,
                1,
                1,
                1,
                1
            ],
            "costs": [
                1.4819736994272683,
                1.4819736994272683,
                1.4819736994272683,
                1.4819736994272683,
                1.4819736994272683
            ]
        },
        {
            "run_id": 1,
            "success": [
                0,
                0,
                0,
                0,
                1
            ],
            "costs": [
                null,
                null,
                null,
                null,
                1.596047015958389
            ]
        },
        {
            "run_id": 2,
            "success": [
                1,
                1,
                1,
                1,
                1
            ],
            "costs": [
                1.3111570922851448,
                1.3111570922851448,
                1.3111570922851448,
                1.3111570922851448,
                1.3111570922851448
            ]
        },
        {
            "run_id": 3,
            "success": [
                0,
                0,
                0,
                0,
                0
            ],
            "costs": [
                null,
                null,
                null,
                null,
                null
            ]
        },
        {
            "run_id": 4,
            "success": [
                0,
                0,
                0,
                0,
                0
            ],
            "costs": [
                null,
                null,
                null,
                null,
                null
            ]
        },
        {
            "run_id": 5,
            "success": [
                1,
                1,
                1,
                1,
                1
            ],
            "costs": [
                1.293375072339131,
                1.293375072339131,
                1.293375072339131,
                1.293375072339131,
                1.293375072339131
            ]
        },
        {
            "run_id": 6,
            "success": [
                1,
                1,
                1,
                1,
                1
            ],
            "costs": [
                1.2473073490286422,
                1.2473073490286422,
                1.2473073490286422,
                1.2473073490286422,
                1.2473073490286422
            ]
        },
        {
            "run_id": 7,
            "success": [
                1,
                1,
                1,
                1,
                1
            ],
            "costs": [
                1.1121300713934634,
                1.1121300713934634,
                1.1121300713934634,
                1.1121300713934634,
                1.1121300713934634
            ]
        },
        {
            "run_id": 8,
            "success": [
                0,
                0,
                0,
                0,
                0
            ],
            "costs": [
                null,
                null,
                null,
                null,
                null
            ]
        },
        {
            "run_id": 9,
            "success": [
                0,
                0,
                0,
                0,
                0
            ],
            "costs": [
                null,
                null,
                null,
                null,
                null
            ]
        },
        {
            "run_id": 10,
            "success": [
                0,
                0,
                0,
                0,
                0
            ],
            "costs": [
                null,
                null,
                null,
                null,
                null
            ]
        },
        {
            "run_id": 11,
            "success": [
                0,
                0,
                0,
                0,
                0
            ],
            "costs": [
                null,
                null,
                null,
                null,
                null
            ]
        },
        {
            "run_id": 12,
            "success": [
                1,
                1,
                1,
                1,
                1
            ],
            "costs": [
                1.328501565163588,
                1.328501565163588,
                1.328501565163588,
                1.328501565163588,
                1.328501565163588
            ]
        },
        {
            "run_id": 13,
            "success": [
                0,
                0,
                0,
                1,
                1
            ],
            "costs": [
                null,
                null,
                null,
                1.196043946003162,
                1.196043946003162
            ]
        },
        {
            "run_id": 14,
            "success": [
                1,
                1,
                1,
                1,
                1
            ],
            "costs": [
                1.0770256291785663,
                1.0770256291785663,
                1.0770256291785663,
                1.0770256291785663,
                1.0770256291785663
            ]
        },
        {
            "run_id": 15,
            "success": [
                0,
                0,
                0,
                0,
                0
            ],
            "costs": [
                null,
                null,
                null,
                null,
                null
            ]
        },
        {
            "run_id": 16,
            "success": [
                0,
                0,
                0,
                0,
                0
            ],
            "costs": [
                null,
                null,
                null,
                null,
                null
            ]
        },
        {
            "run_id": 17,
            "success": [
                0,
                0,
                0,
                1,
                1
            ],
            "costs": [
                null,
                null,
                null,
                1.2625602285934656,
                1.2625602285934656
            ]
        },
        {
            "run_id": 18,
            "success": [
                0,
                0,
                0,
                0,
                0
            ],
            "costs": [
                null,
                null,
                null,
                null,
                null
            ]
        },
        {
            "run_id": 19,
            "success": [
                0,
                1,
                1,
                1,
                1
            ],
            "costs": [
                null,
                1.2249784420348153,
                1.2249784420348153,
                1.2249784420348153,
                1.2249784420348153
            ]
        }
    ]
}